opendp_logger/__init__.py
opendp_logger/deserialize.py
opendp_logger/serialize.py
opendp_logger-0.3.0.dist-info/METADATA
opendp_logger-0.3.0.dist-info/WHEEL
opendp_logger-0.3.0.dist-info/top_level.txt
opendp_logger-0.3.0.dist-info/RECORD
